browser_agent/__init__.py
browser_agent/cli.py
browser_agent/cli_main.py
browser_agent/gui_main.py
browser_agent/browsers/__init__.py
browser_agent/browsers/detector.py
browser_agent/browsers/manager.py
browser_agent/browsers/support.py
browser_agent/config/__init__.py
browser_agent/config/constants.py
browser_agent/config/paths.py
browser_agent/config/settings.py
browser_agent/core/__init__.py
browser_agent/core/agent.py
browser_agent/core/ai_processor.py
browser_agent/core/config.py
browser_agent/core/multi_llm_processor.py
browser_agent/gui/__init__.py
browser_agent/gui/brain_tab.py
browser_agent/gui/browser_tab.py
browser_agent/gui/chat_interface.py
browser_agent/gui/desktop_automation_tab.py
browser_agent/gui/enhanced_browser_tab.py
browser_agent/gui/main_window.py
browser_agent/gui/mcp_tab.py
browser_agent/gui/placeholder_utils.py
browser_agent/gui/settings_tab.py
browser_agent/gui/task_log_tab.py
browser_agent/mcp/__init__.py
browser_agent/mcp/chat_integration.py
browser_agent/mcp/client.py
browser_agent/mcp/marketplace.py
browser_agent/mcp/server_manager.py
browser_agent/mcp/types.py
browser_agent/plugins/__init__.py
browser_agent/plugins/base.py
browser_agent/plugins/registry.py
browser_agent/plugins/builtin/__init__.py
browser_agent/plugins/builtin/ecommerce.py
browser_agent/plugins/builtin/form_filler.py
browser_agent/utils/__init__.py
browser_agent/utils/automation.py
browser_agent/utils/container.py
browser_agent/utils/desktop_automation.py
browser_agent/utils/logger.py
browser_agent/utils/logging_config.py
browser_agent/utils/scheduler.py
browser_agent/utils/unified_automation.py
browser_agent-1.0.0.dist-info/licenses/LICENSE
browser_agent-1.0.0.dist-info/METADATA
browser_agent-1.0.0.dist-info/WHEEL
browser_agent-1.0.0.dist-info/entry_points.txt
browser_agent-1.0.0.dist-info/top_level.txt
browser_agent-1.0.0.dist-info/RECORD
