Metadata-Version: 2.4
Name: browser-agent
Version: 1.0.0
Summary: AI-powered web browser automation with multi-LLM support and modern GUI
Home-page: https://github.com/yourusername/browser-agent
Author: Browser Agent Team
Author-email: Browser Agent Team <aryanvbw@gmail.com>
Maintainer-email: Browser Agent Team <aryanvbw@gmail.com>
License: MIT
Project-URL: Homepage, https://github.com/AryanVBW/browser-agent
Project-URL: Documentation, https://browser-agent.readthedocs.io
Project-URL: Repository, https://github.com/AryanVBW/browser-agent.git
Project-URL: Bug Tracker, https://github.com/AryanVBW/browser-agent/issues
Project-URL: Changelog, https://github.com/AryanVBW/browser-agent/blob/main/CHANGELOG.md
Keywords: automation,browser,ai,selenium,playwright,gui,llm,web-scraping,testing,rpa,natural-language,openai,anthropic,cli,cross-platform,mcp
Platform: any
Classifier: Development Status :: 5 - Production/Stable
Classifier: Intended Audience :: Developers
Classifier: Intended Audience :: End Users/Desktop
Classifier: Intended Audience :: System Administrators
Classifier: License :: OSI Approved :: MIT License
Classifier: Operating System :: OS Independent
Classifier: Operating System :: Microsoft :: Windows
Classifier: Operating System :: POSIX :: Linux
Classifier: Operating System :: MacOS
Classifier: Programming Language :: Python :: 3
Classifier: Programming Language :: Python :: 3.8
Classifier: Programming Language :: Python :: 3.9
Classifier: Programming Language :: Python :: 3.10
Classifier: Programming Language :: Python :: 3.11
Classifier: Programming Language :: Python :: 3.12
Classifier: Programming Language :: Python :: Implementation :: CPython
Classifier: Programming Language :: Python :: Implementation :: PyPy
Classifier: Topic :: Internet :: WWW/HTTP :: Browsers
Classifier: Topic :: Software Development :: Testing
Classifier: Topic :: Software Development :: Libraries :: Python Modules
Classifier: Topic :: System :: Systems Administration
Classifier: Topic :: Utilities
Classifier: Topic :: Scientific/Engineering :: Artificial Intelligence
Classifier: Environment :: Console
Classifier: Environment :: Web Environment
Classifier: Environment :: X11 Applications :: Qt
Classifier: Framework :: Pytest
Classifier: Typing :: Typed
Requires-Python: >=3.8
License-File: LICENSE
Requires-Dist: selenium>=4.15.0
Requires-Dist: webdriver-manager>=4.0.0
Requires-Dist: playwright>=1.40.0
Requires-Dist: beautifulsoup4>=4.12.0
Requires-Dist: requests>=2.31.0
Requires-Dist: openai>=1.3.0
Requires-Dist: python-dotenv>=1.0.0
Requires-Dist: schedule>=1.2.0
Requires-Dist: psutil>=5.9.0
Requires-Dist: colorama>=0.4.0
Requires-Dist: pydantic>=2.5.0
Requires-Dist: typing-extensions>=4.8.0
Requires-Dist: pillow>=10.0.0
Requires-Dist: customtkinter>=5.2.0
Requires-Dist: google-generativeai>=0.3.0
Requires-Dist: anthropic>=0.7.0
Requires-Dist: aiofiles>=23.0.0
Requires-Dist: pyautogui>=0.9.54
Requires-Dist: opencv-python>=4.8.0
Requires-Dist: mcp>=1.0.0
Requires-Dist: jsonrpc-requests>=0.4.0
Requires-Dist: websockets>=12.0
Requires-Dist: aiohttp>=3.9.0
Requires-Dist: click>=8.1.0
Requires-Dist: rich>=13.7.0
Requires-Dist: typer>=0.9.0
Requires-Dist: PyYAML>=6.0.1
Requires-Dist: loguru>=0.7.2
Requires-Dist: tenacity>=8.2.3
Requires-Dist: jinja2>=3.1.2
Requires-Dist: packaging>=23.2
Requires-Dist: platformdirs>=4.1.0
Requires-Dist: cryptography>=41.0.7
Requires-Dist: httpx>=0.25.2
Requires-Dist: asyncio-mqtt>=0.16.1
Requires-Dist: python-multipart>=0.0.6
Requires-Dist: uvloop>=0.19.0; sys_platform != "win32"
Requires-Dist: winloop>=0.1.0; sys_platform == "win32"
Provides-Extra: ai
Requires-Dist: openai>=1.6.0; extra == "ai"
Requires-Dist: anthropic>=0.8.0; extra == "ai"
Requires-Dist: google-generativeai>=0.3.0; extra == "ai"
Requires-Dist: cohere>=4.37; extra == "ai"
Requires-Dist: transformers>=4.36.0; extra == "ai"
Requires-Dist: torch>=2.1.0; extra == "ai"
Requires-Dist: sentence-transformers>=2.2.2; extra == "ai"
Provides-Extra: gui
Requires-Dist: PyQt6>=6.6.0; extra == "gui"
Requires-Dist: PySide6>=6.6.0; extra == "gui"
Requires-Dist: tkinter-tooltip>=2.1.0; extra == "gui"
Requires-Dist: customtkinter>=5.2.0; extra == "gui"
Requires-Dist: ttkbootstrap>=1.10.1; extra == "gui"
Provides-Extra: web
Requires-Dist: fastapi>=0.104.0; extra == "web"
Requires-Dist: uvicorn[standard]>=0.24.0; extra == "web"
Requires-Dist: starlette>=0.27.0; extra == "web"
Requires-Dist: websockets>=12.0; extra == "web"
Requires-Dist: sse-starlette>=1.8.2; extra == "web"
Provides-Extra: db
Requires-Dist: sqlalchemy>=2.0.23; extra == "db"
Requires-Dist: alembic>=1.13.0; extra == "db"
Requires-Dist: asyncpg>=0.29.0; extra == "db"
Requires-Dist: aiosqlite>=0.19.0; extra == "db"
Requires-Dist: redis>=5.0.1; extra == "db"
Requires-Dist: motor>=3.3.2; extra == "db"
Provides-Extra: cloud
Requires-Dist: boto3>=1.34.0; extra == "cloud"
Requires-Dist: azure-storage-blob>=12.19.0; extra == "cloud"
Requires-Dist: google-cloud-storage>=2.10.0; extra == "cloud"
Requires-Dist: kubernetes>=28.1.0; extra == "cloud"
Requires-Dist: docker>=6.1.3; extra == "cloud"
Provides-Extra: monitoring
Requires-Dist: prometheus-client>=0.19.0; extra == "monitoring"
Requires-Dist: opentelemetry-api>=1.21.0; extra == "monitoring"
Requires-Dist: opentelemetry-sdk>=1.21.0; extra == "monitoring"
Requires-Dist: opentelemetry-instrumentation>=0.42b0; extra == "monitoring"
Requires-Dist: sentry-sdk>=1.38.0; extra == "monitoring"
Requires-Dist: structlog>=23.2.0; extra == "monitoring"
Provides-Extra: dev
Requires-Dist: pytest>=7.4.3; extra == "dev"
Requires-Dist: pytest-cov>=4.1.0; extra == "dev"
Requires-Dist: pytest-mock>=3.12.0; extra == "dev"
Requires-Dist: pytest-asyncio>=0.21.1; extra == "dev"
Requires-Dist: pytest-xdist>=3.5.0; extra == "dev"
Requires-Dist: pytest-html>=4.1.1; extra == "dev"
Requires-Dist: pytest-benchmark>=4.0.0; extra == "dev"
Requires-Dist: black>=23.11.0; extra == "dev"
Requires-Dist: isort>=5.12.0; extra == "dev"
Requires-Dist: flake8>=6.1.0; extra == "dev"
Requires-Dist: mypy>=1.7.1; extra == "dev"
Requires-Dist: pylint>=3.0.3; extra == "dev"
Requires-Dist: bandit>=1.7.5; extra == "dev"
Requires-Dist: safety>=2.3.5; extra == "dev"
Requires-Dist: pre-commit>=3.6.0; extra == "dev"
Requires-Dist: tox>=4.11.4; extra == "dev"
Requires-Dist: coverage>=7.3.2; extra == "dev"
Requires-Dist: sphinx>=7.2.6; extra == "dev"
Requires-Dist: sphinx-rtd-theme>=1.3.0; extra == "dev"
Requires-Dist: myst-parser>=2.0.0; extra == "dev"
Requires-Dist: build>=1.0.3; extra == "dev"
Requires-Dist: twine>=4.0.2; extra == "dev"
Requires-Dist: wheel>=0.42.0; extra == "dev"
Requires-Dist: setuptools-scm>=8.0.4; extra == "dev"
Requires-Dist: pip-tools>=7.3.0; extra == "dev"
Requires-Dist: bump2version>=1.0.1; extra == "dev"
Requires-Dist: gitpython>=3.1.40; extra == "dev"
Requires-Dist: watchdog>=3.0.0; extra == "dev"
Requires-Dist: ipython>=8.17.2; extra == "dev"
Requires-Dist: ipdb>=0.13.13; extra == "dev"
Requires-Dist: jupyter>=1.0.0; extra == "dev"
Requires-Dist: notebook>=7.0.6; extra == "dev"
Requires-Dist: memory-profiler>=0.61.0; extra == "dev"
Requires-Dist: line-profiler>=4.1.1; extra == "dev"
Requires-Dist: py-spy>=0.3.14; extra == "dev"
Provides-Extra: test
Requires-Dist: pytest>=7.4.3; extra == "test"
Requires-Dist: pytest-cov>=4.1.0; extra == "test"
Requires-Dist: pytest-mock>=3.12.0; extra == "test"
Requires-Dist: pytest-asyncio>=0.21.1; extra == "test"
Requires-Dist: pytest-xdist>=3.5.0; extra == "test"
Requires-Dist: pytest-html>=4.1.1; extra == "test"
Requires-Dist: pytest-benchmark>=4.0.0; extra == "test"
Requires-Dist: pytest-timeout>=2.2.0; extra == "test"
Requires-Dist: pytest-repeat>=0.9.3; extra == "test"
Requires-Dist: pytest-randomly>=3.15.0; extra == "test"
Requires-Dist: pytest-sugar>=0.9.7; extra == "test"
Requires-Dist: pytest-clarity>=1.0.1; extra == "test"
Requires-Dist: factory-boy>=3.3.0; extra == "test"
Requires-Dist: faker>=20.1.0; extra == "test"
Requires-Dist: responses>=0.24.1; extra == "test"
Requires-Dist: httpx>=0.25.2; extra == "test"
Requires-Dist: aioresponses>=0.7.4; extra == "test"
Requires-Dist: freezegun>=1.2.2; extra == "test"
Requires-Dist: time-machine>=2.13.0; extra == "test"
Provides-Extra: docs
Requires-Dist: sphinx>=7.2.6; extra == "docs"
Requires-Dist: sphinx-rtd-theme>=1.3.0; extra == "docs"
Requires-Dist: sphinx-autodoc-typehints>=1.25.2; extra == "docs"
Requires-Dist: myst-parser>=2.0.0; extra == "docs"
Requires-Dist: sphinx-copybutton>=0.5.2; extra == "docs"
Requires-Dist: sphinx-design>=0.5.0; extra == "docs"
Requires-Dist: sphinxcontrib-mermaid>=0.9.2; extra == "docs"
Requires-Dist: sphinx-tabs>=3.4.4; extra == "docs"
Requires-Dist: sphinx-togglebutton>=0.3.2; extra == "docs"
Requires-Dist: nbsphinx>=0.9.3; extra == "docs"
Requires-Dist: pandoc>=2.3; extra == "docs"
Requires-Dist: docutils>=0.20.1; extra == "docs"
Provides-Extra: all
Requires-Dist: browser-agent[ai,cloud,db,gui,monitoring,web]; extra == "all"
Provides-Extra: full
Requires-Dist: browser-agent[all,dev,docs,test]; extra == "full"
Dynamic: author
Dynamic: home-page
Dynamic: license-file
Dynamic: platform
Dynamic: requires-python
